codeakshcalculator/__init__.py
codeakshcalculator-0.1.0.dist-info/licenses/LICENSE.txt
codeakshcalculator-0.1.0.dist-info/METADATA
codeakshcalculator-0.1.0.dist-info/WHEEL
codeakshcalculator-0.1.0.dist-info/top_level.txt
codeakshcalculator-0.1.0.dist-info/RECORD
