Metadata-Version: 2.4
Name: codeakshcalculator
Version: 0.1.0
Summary: An calculator Python package
Author: Akshata Kagale
Author-email: kagaleakshata26@gmail.com
Classifier: Programming Language :: Python :: 3
Classifier: License :: OSI Approved :: MIT License
Classifier: Operating System :: OS Independent
License-File: LICENSE.txt
Dynamic: author
Dynamic: author-email
Dynamic: classifier
Dynamic: license-file
Dynamic: summary
